larva/__init__.py
larva/image_capture.py
larva/inference.py
larva/lighting_control.py
larva/motion_control.py
larva/utils.py
larva_lib-0.0.0.4.dist-info/LICENSE
larva_lib-0.0.0.4.dist-info/METADATA
larva_lib-0.0.0.4.dist-info/WHEEL
larva_lib-0.0.0.4.dist-info/top_level.txt
larva_lib-0.0.0.4.dist-info/RECORD
